riskalphaindics/__init__.py
riskalphaindics/main.py
riskalphaindics-0.1.0.dist-info/LICENSE
riskalphaindics-0.1.0.dist-info/METADATA
riskalphaindics-0.1.0.dist-info/WHEEL
riskalphaindics-0.1.0.dist-info/RECORD
