Metadata-Version: 2.1
Name: riskalphaindics
Version: 0.1.0
Summary: Trading indicators for RiskAlpha trading bots.
Author: Niclas Hummel
Author-email: info@algoinvest.online
Requires-Python: >=3.12,<4.0
Classifier: Programming Language :: Python :: 3
Classifier: Programming Language :: Python :: 3.12
Requires-Dist: numpy
Requires-Dist: pandas
